Metadata-Version: 2.1
Name: easycanvas
Version: 1.1
Summary: Make canvas easier.
Home-page: https://github.com/Dlunhappy226/easycanvas
Author: Dlunhappy226
Author-email: dlunhappy226@gmail.com
License: MIT
Download-URL: https://github.com/Dlunhappy226/easycanvas/archive/1.1.tar.gz
Platform: UNKNOWN
License-File: LICENSE
